monasca_transform/__init__.py
monasca_transform/log_utils.py
monasca_transform/mysql_offset_specs.py
monasca_transform/offset_specs.py
monasca_transform/component/__init__.py
monasca_transform/component/component_utils.py
monasca_transform/component/insert/__init__.py
monasca_transform/component/insert/kafka_insert.py
monasca_transform/component/insert/kafka_insert_pre_hourly.py
monasca_transform/component/insert/prepare_data.py
monasca_transform/component/setter/__init__.py
monasca_transform/component/setter/pre_hourly_calculate_rate.py
monasca_transform/component/setter/rollup_quantity.py
monasca_transform/component/setter/set_aggregated_metric_name.py
monasca_transform/component/setter/set_aggregated_period.py
monasca_transform/component/usage/__init__.py
monasca_transform/component/usage/calculate_rate.py
monasca_transform/component/usage/fetch_quantity.py
monasca_transform/component/usage/fetch_quantity_util.py
monasca_transform/config/__init__.py
monasca_transform/config/config_initializer.py
monasca_transform/data_driven_specs/__init__.py
monasca_transform/data_driven_specs/data_driven_specs_repo.py
monasca_transform/data_driven_specs/mysql_data_driven_specs_repo.py
monasca_transform/data_driven_specs/pre_transform_specs/pre_transform_specs.json
monasca_transform/data_driven_specs/transform_specs/transform_specs.json
monasca_transform/db/__init__.py
monasca_transform/db/db_utils.py
monasca_transform/driver/__init__.py
monasca_transform/driver/mon_metrics_kafka.py
monasca_transform/messaging/__init__.py
monasca_transform/messaging/adapter.py
monasca_transform/processor/__init__.py
monasca_transform/processor/pre_hourly_processor.py
monasca_transform/processor/processor_util.py
monasca_transform/service/__init__.py
monasca_transform/service/transform_service.py
monasca_transform/transform/__init__.py
monasca_transform/transform/storage_utils.py
monasca_transform/transform/transform_utils.py
monasca_transform-2.0.0.dist-info/DESCRIPTION.rst
monasca_transform-2.0.0.dist-info/METADATA
monasca_transform-2.0.0.dist-info/RECORD
monasca_transform-2.0.0.dist-info/WHEEL
monasca_transform-2.0.0.dist-info/entry_points.txt
monasca_transform-2.0.0.dist-info/metadata.json
monasca_transform-2.0.0.dist-info/pbr.json
monasca_transform-2.0.0.dist-info/top_level.txt
