Metadata-Version: 2.0
Name: monasca-transform
Version: 2.0.0
Summary: Data Aggregation and Transformation component for Monasca
Home-page: https://wiki.openstack.org/wiki/Monasca/Transform
Author: OpenStack
Author-email: openstack-discuss@lists.openstack.org
License: UNKNOWN
Platform: UNKNOWN
Classifier: Environment :: OpenStack
Classifier: Intended Audience :: Information Technology
Classifier: Intended Audience :: System Administrators
Classifier: License :: OSI Approved :: Apache Software License
Classifier: Operating System :: POSIX :: Linux
Classifier: Programming Language :: Python
Classifier: Programming Language :: Python :: Implementation :: CPython
Classifier: Programming Language :: Python :: 3 :: Only
Classifier: Programming Language :: Python :: 3
Classifier: Programming Language :: Python :: 3.6
Classifier: Programming Language :: Python :: 3.7
Requires-Python: >=3.6
Requires-Dist: PyMySQL (>=0.7.6)
Requires-Dist: SQLAlchemy (!=1.1.5,!=1.1.6,!=1.1.7,!=1.1.8,>=1.0.10)
Requires-Dist: monasca-common (>=2.7.0)
Requires-Dist: oslo.config (>=5.2.0)
Requires-Dist: oslo.log (>=3.36.0)
Requires-Dist: oslo.service (!=1.28.1,>=1.24.0)
Requires-Dist: pbr (!=2.1.0,>=2.0.0)
Requires-Dist: psutil (>=3.2.2)
Requires-Dist: six (>=1.10.0)
Requires-Dist: stevedore (>=1.20.0)
Requires-Dist: tooz (>=1.58.0)
